cycolorcrop/LICENSE
cycolorcrop/README.md
cycolorcrop/__init__.py
cycolorcrop/colorcrop.hpp
cycolorcrop/imagecrop.png
cycolorcrop/requirements.txt
cycolorcrop/thirdparty.json
cycolorcrop/uiev.pyx
cycolorcrop/uiev_compile.py
cycolorcrop-0.10.dist-info/LICENSE.rst
cycolorcrop-0.10.dist-info/METADATA
cycolorcrop-0.10.dist-info/WHEEL
cycolorcrop-0.10.dist-info/top_level.txt
cycolorcrop-0.10.dist-info/RECORD
