Metadata-Version: 2.1
Name: cycolorcrop
Version: 0.10
Summary: Crops an image based on allowed colors
Home-page: https://github.com/hansalemaos/cycolorcrop
Author: Johannes Fischer
Author-email: aulasparticularesdealemaosp@gmail.com
License: MIT
Keywords: Cython,Crop,Image
Classifier: Development Status :: 4 - Beta
Classifier: Programming Language :: Python :: 3 :: Only
Classifier: Programming Language :: Python :: 3.10
Classifier: Topic :: Software Development :: Libraries :: Python Modules
Classifier: Topic :: Utilities
License-File: LICENSE.rst
Requires-Dist: Cython
Requires-Dist: numpy
Requires-Dist: setuptools
